prasanthmongo/__init__.py
prasanthmongo/mongoclient.py
mongo_prasanth-2.0.0.dist-info/METADATA
mongo_prasanth-2.0.0.dist-info/WHEEL
mongo_prasanth-2.0.0.dist-info/top_level.txt
mongo_prasanth-2.0.0.dist-info/RECORD
