Metadata-Version: 2.1
Name: mongo-prasanth
Version: 2.0.0
Summary: Demo library
Author: prasanth
Author-email: prasanth@email.com
License: private
Classifier: Intended Audience :: Developers
Classifier: Programming Language :: Python
Classifier: Programming Language :: Python :: 3
Classifier: Programming Language :: Python :: 3.6
Classifier: Programming Language :: Python :: 3.7
Classifier: Programming Language :: Python :: 3.8
Classifier: Programming Language :: Python :: 3.9
Classifier: Operating System :: OS Independent
Requires-Dist: pymongo
